meni/__init__.py
meni/__main__.py
meni/app.py
meni/model/model.py
meni/rc_assets.py
meni/theme.py
meni/ui/common.py
meni/ui/docks/browser.py
meni/ui/docks/collectionproperties.py
meni/ui/docks/fileproperties.py
meni/ui/docks/viewer.py
meni/ui/filestable.py
meni/ui/flowlayout.py
meni/ui/menus/filecontextmenu.py
meni/ui/menus/menusettings.py
meni/ui/propertyrowwithapply.py
meni/ui/searchinput.py
meni/ui/tagrow.py
meni/ui/windows/importdialog.py
meni/ui/windows/mainwindow.py
meni/ui/windows/welcome.py
meni/utils.py
meni/worker.py
meni-0.1.5.dist-info/LICENSE
meni-0.1.5.dist-info/METADATA
meni-0.1.5.dist-info/WHEEL
meni-0.1.5.dist-info/entry_points.txt
meni-0.1.5.dist-info/RECORD
