Metadata-Version: 2.1
Name: meni
Version: 0.1.5
Summary: Software to manage a library of 3d files (stl)
Home-page: https://github.com/diesphink/meni
License: BSD-3-Clause
Author: Diego Pereyra
Author-email: diego@diegopereyra.com
Requires-Python: >=3.9,<3.13
Classifier: Development Status :: 3 - Alpha
Classifier: Environment :: X11 Applications :: Qt
Classifier: Intended Audience :: Developers
Classifier: Intended Audience :: End Users/Desktop
Classifier: License :: OSI Approved :: BSD License
Classifier: Operating System :: MacOS :: MacOS X
Classifier: Operating System :: Microsoft :: Windows
Classifier: Operating System :: POSIX :: Linux
Classifier: Programming Language :: Python
Classifier: Programming Language :: Python :: 3
Classifier: Programming Language :: Python :: 3.9
Classifier: Programming Language :: Python :: 3.10
Classifier: Programming Language :: Python :: 3.11
Classifier: Programming Language :: Python :: 3.12
Requires-Dist: jsonpickle (>=3.0.4,<4.0.0)
Requires-Dist: matplotlib (>=3.8.4,<4.0.0)
Requires-Dist: numpy-stl (>=3.1.1,<4.0.0)
Requires-Dist: pyinstaller (>=6.6.0,<7.0.0)
Requires-Dist: pyside6 (>=6.7.0,<7.0.0)
Requires-Dist: qt-material (>=2.14,<3.0)
Requires-Dist: qtawesome (>=1.3.1,<2.0.0)
Requires-Dist: vtkplotlib (>=2.1.1,<3.0.0)
Project-URL: Repository, https://github.com/diesphink/meni
